omninumeric/__init__.py
omninumeric/omninumeric.py
omninumeric/cyrillic/__init__.py
omninumeric/cyrillic/cyrillic.py
omninumeric/greek/__init__.py
omninumeric/greek/greek.py
omninumeric/greek/old.py
omninumeric/roman/__init__.py
omninumeric/roman/roman.py
tests/__init__.py
tests/test_cyrillic.py
tests/test_roman.py
omninumeric-2.1.0.dist-info/METADATA
omninumeric-2.1.0.dist-info/WHEEL
omninumeric-2.1.0.dist-info/top_level.txt
omninumeric-2.1.0.dist-info/RECORD
