Metadata-Version: 2.1
Name: omninumeric
Version: 2.1.0
Summary: Read and write numbers in alphabetic numeral systems
Home-page: https://github.com/endrain/omninumeric
Author: Andrei Shur
Author-email: amshoor@gmail.com
License: MIT
Keywords: church slavonic,roman,arabic,number,conversion
Classifier: Development Status :: 4 - Beta
Classifier: Programming Language :: Python :: 3
Classifier: Programming Language :: Python :: 3.4
Classifier: Programming Language :: Python :: 3.5
Classifier: Programming Language :: Python :: 3.6
Classifier: Programming Language :: Python :: 3.7
Classifier: Programming Language :: Python :: 3.8
Classifier: Programming Language :: Python :: 3.9
Classifier: Programming Language :: Python :: 3.10
Classifier: License :: OSI Approved :: MIT License
Classifier: Operating System :: OS Independent
Classifier: Topic :: Scientific/Engineering :: Mathematics
Classifier: Topic :: Software Development :: Libraries
Classifier: Topic :: Software Development :: Localization
Classifier: Intended Audience :: Developers
Classifier: Intended Audience :: Religion
Classifier: Intended Audience :: Science/Research
Requires-Python: >=3.4
